excusegen/__init__.py
excusegen/__main__.py
excusegen/main.py
excusegen-0.1.2.dist-info/licenses/LICENSE
excusegen-0.1.2.dist-info/METADATA
excusegen-0.1.2.dist-info/WHEEL
excusegen-0.1.2.dist-info/top_level.txt
excusegen-0.1.2.dist-info/RECORD
