Metadata-Version: 2.4
Name: excusegen
Version: 0.1.2
Summary: Generates bad excuses
Author: Team Ember
Requires-Python: >=3.8
License-File: LICENSE
Dynamic: license-file
